zueai/__init__.py
zueai-0.1.0.dist-info/METADATA
zueai-0.1.0.dist-info/WHEEL
zueai-0.1.0.dist-info/RECORD
