Metadata-Version: 2.4
Name: zueai
Version: 0.1.0
Summary: Zue AI
Project-URL: Homepage, https://github.com/zueai/zueai
Author-email: Your Name <your.email@example.com>
Classifier: License :: OSI Approved :: MIT License
Classifier: Operating System :: OS Independent
Classifier: Programming Language :: Python :: 3
Requires-Python: >=3.7
